setup.cfg
setup.py
shado_client/__init__.py
shado_client/api_client.py
shado_client/configuration.py
shado_client/rest.py
shado_client.egg-info/PKG-INFO
shado_client.egg-info/SOURCES.txt
shado_client.egg-info/dependency_links.txt
shado_client.egg-info/requires.txt
shado_client.egg-info/top_level.txt
shado_client/api/__init__.py
shado_client/api/account_api.py
shado_client/api/group_api.py
shado_client/api/invitation_api.py
shado_client/api/item_api.py
shado_client/api/membership_api.py
shado_client/api/plugin_api.py
shado_client/api/plugin_instance_api.py
shado_client/api/result_api.py
shado_client/api/sharing_api.py
shado_client/models/__init__.py
shado_client/models/account.py
shado_client/models/group.py
shado_client/models/inline_response_200.py
shado_client/models/inline_response_200_1.py
shado_client/models/inline_response_200_2.py
shado_client/models/inline_response_200_3.py
shado_client/models/invitation.py
shado_client/models/item.py
shado_client/models/membership.py
shado_client/models/object_id.py
shado_client/models/plugin.py
shado_client/models/plugin_instance.py
shado_client/models/result.py
shado_client/models/sharing.py
shado_client/models/x_any.py