Metadata-Version: 1.0
Name: shado-client
Version: 0.0.4
Summary: shado
Home-page: UNKNOWN
Author: UNKNOWN
Author-email: UNKNOWN
License: UNKNOWN
Keywords: shado,rest,api
Platform: UNKNOWN
